[
  {
    "file": "7887036.12_1.pdf",
    "cover_address": "17642 BEACH BLVD",
    "latitude": "N/A",
    "longitude": "N/A",
    "real_physical_location": "Unknown / Map Coordinates"
  },
  {
    "file": "7887036.15.pdf",
    "cover_address": "17631 CAMERON LN",
    "latitude": "N/A",
    "longitude": "N/A",
    "real_physical_location": "Unknown / Map Coordinates"
  },
  {
    "file": "7887036.16.pdf",
    "cover_address": "17631 CAMERON LN",
    "latitude": "N/A",
    "longitude": "N/A",
    "real_physical_location": "Unknown / Map Coordinates"
  },
  {
    "file": "7887036.24_1.pdf",
    "cover_address": "17631 CAMERON LN",
    "latitude": "N/A",
    "longitude": "N/A",
    "real_physical_location": "Unknown / Map Coordinates"
  },
  {
    "file": "7887036.3 (1).pdf",
    "cover_address": "17642 BEACH BLVD",
    "latitude": "N/A",
    "longitude": "N/A",
    "real_physical_location": "Unknown / Map Coordinates"
  },
  {
    "file": "7887036.3.pdf",
    "cover_address": "17642 BEACH BLVD",
    "latitude": "N/A",
    "longitude": "N/A",
    "real_physical_location": "Unknown / Map Coordinates"
  },
  {
    "file": "7887036.4 (1).pdf",
    "cover_address": "17642 BEACH BLVD",
    "latitude": "N/A",
    "longitude": "N/A",
    "real_physical_location": "Unknown / Map Coordinates"
  },
  {
    "file": "7887036.4.pdf",
    "cover_address": "17642 BEACH BLVD",
    "latitude": "N/A",
    "longitude": "N/A",
    "real_physical_location": "Unknown / Map Coordinates"
  },
  {
    "file": "788703618.PDF",
    "cover_address": "17631 CAMERON LN",
    "latitude": "N/A",
    "longitude": "N/A",
    "real_physical_location": "Unknown / Map Coordinates"
  },
  {
    "file": "788703618_2.PDF",
    "cover_address": "17631 CAMERON LN",
    "latitude": "N/A",
    "longitude": "N/A",
    "real_physical_location": "Unknown / Map Coordinates"
  },
  {
    "file": "788703620.PDF",
    "cover_address": "17631 CAMERON LN",
    "latitude": "N/A",
    "longitude": "N/A",
    "real_physical_location": "Unknown / Map Coordinates"
  },
  {
    "file": "788703620_2.PDF",
    "cover_address": "17631 CAMERON LN",
    "latitude": "N/A",
    "longitude": "N/A",
    "real_physical_location": "Unknown / Map Coordinates"
  },
  {
    "file": "78870367 (1).PDF",
    "cover_address": "17642 BEACH BLVD",
    "latitude": "N/A",
    "longitude": "N/A",
    "real_physical_location": "Unknown / Map Coordinates"
  },
  {
    "file": "78870367.PDF",
    "cover_address": "17642 BEACH BLVD",
    "latitude": "N/A",
    "longitude": "N/A",
    "real_physical_location": "Unknown / Map Coordinates"
  },
  {
    "file": "78870367_2.PDF",
    "cover_address": "17642 BEACH BLVD",
    "latitude": "N/A",
    "longitude": "N/A",
    "real_physical_location": "Unknown / Map Coordinates"
  },
  {
    "file": "78870369 (1).PDF",
    "cover_address": "17642 BEACH BLVD",
    "latitude": "N/A",
    "longitude": "N/A",
    "real_physical_location": "Unknown / Map Coordinates"
  },
  {
    "file": "78870369 (2).PDF",
    "cover_address": "17642 BEACH BLVD",
    "latitude": "N/A",
    "longitude": "N/A",
    "real_physical_location": "Unknown / Map Coordinates"
  },
  {
    "file": "78870369 (3).PDF",
    "cover_address": "17642 BEACH BLVD",
    "latitude": "N/A",
    "longitude": "N/A",
    "real_physical_location": "Unknown / Map Coordinates"
  },
  {
    "file": "78870369.PDF",
    "cover_address": "17642 BEACH BLVD",
    "latitude": "N/A",
    "longitude": "N/A",
    "real_physical_location": "Unknown / Map Coordinates"
  },
  {
    "file": "78870369_2.PDF",
    "cover_address": "17642 BEACH BLVD",
    "latitude": "N/A",
    "longitude": "N/A",
    "real_physical_location": "Unknown / Map Coordinates"
  },
  {
    "file": "7969270.2s (1).pdf",
    "cover_address": "NOT FOUND",
    "latitude": "118.009042-118032.546997",
    "longitude": "84.",
    "real_physical_location": "Unknown / Map Coordinates"
  },
  {
    "file": "7969270.2s (2).pdf",
    "cover_address": "NOT FOUND",
    "latitude": "118.009042-118032.546997",
    "longitude": "84.",
    "real_physical_location": "Unknown / Map Coordinates"
  },
  {
    "file": "7969270.2s (3).pdf",
    "cover_address": "NOT FOUND",
    "latitude": "118.009042-118032.546997",
    "longitude": "84.",
    "real_physical_location": "Unknown / Map Coordinates"
  },
  {
    "file": "7969270.2s.pdf",
    "cover_address": "NOT FOUND",
    "latitude": "118.009042-118032.546997",
    "longitude": "84.",
    "real_physical_location": "Unknown / Map Coordinates"
  },
  {
    "file": "7969270_2.pdf",
    "cover_address": "NOT FOUND",
    "latitude": "118.0090420-118032.55",
    "longitude": "11",
    "real_physical_location": "Unknown / Map Coordinates"
  },
  {
    "file": "SUMMARY_RADIUS_7969270_2.pdf",
    "cover_address": "NOT FOUND",
    "latitude": "118.0090420-118032.55",
    "longitude": "11",
    "real_physical_location": "Unknown / Map Coordinates"
  }
]